blitz/__init__.py
blitz/losses/__init__.py
blitz/losses/kl_divergence.py
blitz/losses/tests/__init__.py
blitz/losses/tests/kl_divergence_test.py
blitz/models/__init__.py
blitz/models/b_vgg.py
blitz/modules/__init__.py
blitz/modules/base_bayesian_module.py
blitz/modules/conv_bayesian_layer.py
blitz/modules/embedding_bayesian_layer.py
blitz/modules/gru_bayesian_layer.py
blitz/modules/linear_bayesian_layer.py
blitz/modules/lstm_bayesian_layer.py
blitz/modules/weight_sampler.py
blitz/modules/tests/__init__.py
blitz/modules/tests/base_bayesian_module_test.py
blitz/modules/tests/conv_bayesian_layer_test.py
blitz/modules/tests/embadding_bayesian_test.py
blitz/modules/tests/gru_bayesian_layer_test.py
blitz/modules/tests/linear_bayesian_layer_test.py
blitz/modules/tests/lstm_bayesian_layer_test.py
blitz/modules/tests/weight_sampler_test.py
blitz/utils/__init__.py
blitz/utils/layer_wrappers.py
blitz/utils/minibatch_weighting.py
blitz/utils/variational_estimator.py
blitz/utils/tests/__init__.py
blitz/utils/tests/layer_wrappers_test.py
blitz/utils/tests/variational_estimator_test.py
blitz_bayesian_pytorch-0.2.8.dist-info/LICENSE
blitz_bayesian_pytorch-0.2.8.dist-info/METADATA
blitz_bayesian_pytorch-0.2.8.dist-info/WHEEL
blitz_bayesian_pytorch-0.2.8.dist-info/top_level.txt
blitz_bayesian_pytorch-0.2.8.dist-info/RECORD
