Metadata-Version: 2.1
Name: blitz-bayesian-pytorch
Version: 0.2.8
Summary: A simple and extensible library to create Bayesian Neural Network Layers on PyTorch without trouble and with full integration with nn.Module and nn.Sequential.
Home-page: https://github.com/piEsposito/blitz-bayesian-deep-learning
Author: Pi Esposito
License: UNKNOWN
Platform: UNKNOWN
Classifier: Development Status :: 3 - Alpha
Classifier: Intended Audience :: Developers
Classifier: Programming Language :: Python :: 3.7
License-File: LICENSE
Requires-Dist: torch (>=1.7.0)
Requires-Dist: torchvision (>=0.5.0)
Requires-Dist: numpy
Requires-Dist: scikit-learn (>=0.22.2)
Requires-Dist: pillow (>=7.1)
